tests/__init__.py
tests/test_core/__init__.py
tests/test_core/test_service.py
tests/test_extensions/__init__.py
tests/test_extensions/test_anonymous.py
tests/test_extensions/test_snowflake.py
tests/test_extensions/test_sonyflake.py
yzid/__init__.py
yzid/__main__.py
yzid/core/__init__.py
yzid/core/base.py
yzid/core/convert.py
yzid/core/meta.py
yzid/core/populate.py
yzid/core/service.py
yzid/extras/__init__.py
yzid/extras/anonymous.py
yzid/extras/snowflake.py
yzid/extras/sonyflake.py
yzid/populator/__init__.py
yzid/populator/atomic_populator.py
yzid/populator/lock_populator.py
yzid/populator/sync_populator.py
yzid/utils/__init__.py
yzid-0.1.0.dist-info/LICENSE
yzid-0.1.0.dist-info/METADATA
yzid-0.1.0.dist-info/WHEEL
yzid-0.1.0.dist-info/top_level.txt
yzid-0.1.0.dist-info/RECORD
