Metadata-Version: 2.1
Name: yzid
Version: 0.1.0
Summary: An ID generator for distributed microservices.
Home-page: https://github.com/ml444/yz-id.git
Author: cml
Author-email: caimengli0660@gmail.com
License: UNKNOWN
Platform: UNKNOWN
Classifier: Programming Language :: Python :: 3
Classifier: License :: OSI Approved :: MIT License
Classifier: Operating System :: OS Independent
Requires-Python: >=3.6
